master_slave/master.py
master_slave/slave.py
master_slave-1.0.2.dist-info/LICENSE
master_slave-1.0.2.dist-info/METADATA
master_slave-1.0.2.dist-info/WHEEL
master_slave-1.0.2.dist-info/entry_points.txt
master_slave-1.0.2.dist-info/top_level.txt
master_slave-1.0.2.dist-info/RECORD
